napari_medical_image_formats/__init__.py
napari_medical_image_formats/_reader.py
napari_medical_image_formats/_version.py
napari_medical_image_formats/_writer.py
napari_medical_image_formats/_tests/__init__.py
napari_medical_image_formats/_tests/test_reader.py
napari_medical_image_formats-0.3.8.dist-info/LICENSE
napari_medical_image_formats-0.3.8.dist-info/METADATA
napari_medical_image_formats-0.3.8.dist-info/WHEEL
napari_medical_image_formats-0.3.8.dist-info/entry_points.txt
napari_medical_image_formats-0.3.8.dist-info/top_level.txt
napari_medical_image_formats-0.3.8.dist-info/RECORD
