Metadata-Version: 2.1
Name: napari-medical-image-formats
Version: 0.3.8
Summary: A Plugin in order to read medical image formats such as DICOM and NIfTI
Home-page: https://github.com/MBPhys/napari-medical-image-formats
Author: Marc Boucsein, Marc Buckmakowski
License: BSD-3
Platform: UNKNOWN
Classifier: Development Status :: 4 - Beta
Classifier: Intended Audience :: Developers
Classifier: Framework :: napari
Classifier: Topic :: Software Development :: Testing
Classifier: Programming Language :: Python
Classifier: Programming Language :: Python :: 3
Classifier: Programming Language :: Python :: 3.7
Classifier: Programming Language :: Python :: 3.8
Classifier: Programming Language :: Python :: 3.9
Classifier: Operating System :: OS Independent
Classifier: License :: OSI Approved :: BSD License
Requires-Python: >=3.7
License-File: LICENSE
Requires-Dist: napari-plugin-engine (>=0.1.4)
Requires-Dist: numpy
Requires-Dist: pydicom
Requires-Dist: SimpleITK
Requires-Dist: itk
Requires-Dist: itk-napari-conversion
